yt_dlp_plugins/extractor/dtube.py
ytdlp_dtube-2023.12.27.dist-info/LICENSE
ytdlp_dtube-2023.12.27.dist-info/METADATA
ytdlp_dtube-2023.12.27.dist-info/WHEEL
ytdlp_dtube-2023.12.27.dist-info/top_level.txt
ytdlp_dtube-2023.12.27.dist-info/RECORD
