Metadata-Version: 2.1
Name: ytdlp-dtube
Version: 2023.12.27
Summary: yt-dlp extractor for d.tube
Home-page: https://github.com/flashdagger/ytdlp-plugins/tree/dtube
Author: flashdagger
Author-email: flashdagger@googlemail.com
License: The Unlicense
Keywords: yt-dlp,youtube-dl,dtube,extractors,plugins
Platform: any
Classifier: Development Status :: 4 - Beta
Classifier: License :: OSI Approved :: The Unlicense (Unlicense)
Classifier: Programming Language :: Python :: 3
Classifier: Programming Language :: Python :: 3.7
Classifier: Programming Language :: Python :: 3.8
Classifier: Programming Language :: Python :: 3.9
Classifier: Programming Language :: Python :: 3.10
Classifier: Programming Language :: Python :: 3.11
Classifier: Programming Language :: Python :: Implementation
Classifier: Programming Language :: Python :: Implementation :: CPython
Classifier: Programming Language :: Python :: Implementation :: PyPy
Classifier: Operating System :: OS Independent
Classifier: Environment :: Console
Classifier: Environment :: Plugins
Classifier: Topic :: Multimedia :: Video
Requires-Python: >=3.7
License-File: LICENSE
Requires-Dist: yt-dlp >=2023.01.06
Requires-Dist: ytdlp-plugins >=2023.01.08
